classes/bhi_sdg.py
pybhisdg-0.0.0.dist-info/licenses/LICENSE
pybhisdg-0.0.0.dist-info/METADATA
pybhisdg-0.0.0.dist-info/WHEEL
pybhisdg-0.0.0.dist-info/top_level.txt
pybhisdg-0.0.0.dist-info/RECORD
