Metadata-Version: 2.4
Name: PyBHISDG
Version: 0.0.0
Summary: Package for estimating Brain-Heart Interplay using the SDG model
Author-email: Alexander Borch Kristensen <albok@dtu.dk>, Matteo Saibene <saima@dtu.dk>
License: Copyright (C) 2025 Alexander Borch Kristensen
Classifier: Programming Language :: Python :: 3
Classifier: Operating System :: OS Independent
Requires-Python: >=3.9
License-File: LICENSE
Requires-Dist: numpy>=2.3.3
Requires-Dist: scipy>=1.16.2
Requires-Dist: joblib>=1.5.2
Requires-Dist: numba>=0.62.1
Dynamic: license-file
